{
  "annotations": {
    "list": [
      {
        "builtIn": 1,
        "datasource": {
          "type": "grafana",
          "uid": "-- Grafana --"
        },
        "enable": true,
        "hide": true,
        "iconColor": "rgba(0, 211, 255, 1)",
        "name": "Annotations & Alerts",
        "type": "dashboard"
      }
    ]
  },
  "editable": true,
  "fiscalYearStartMonth": 0,
  "graphTooltip": 0,
  "id": 10,
  "links": [],
  "panels": [
    {
      "datasource": {
        "type": "prometheus",
        "uid": "P7A0D6631BB10B34F"
      },
      "fieldConfig": {
        "defaults": {
          "color": {
            "mode": "palette-classic"
          },
          "custom": {
            "axisBorderShow": false,
            "axisCenteredZero": false,
            "axisColorMode": "text",
            "axisLabel": "",
            "axisPlacement": "auto",
            "barAlignment": 0,
            "barWidthFactor": 0.6,
            "drawStyle": "line",
            "fillOpacity": 0,
            "gradientMode": "none",
            "hideFrom": {
              "legend": false,
              "tooltip": false,
              "viz": false
            },
            "insertNulls": false,
            "lineInterpolation": "linear",
            "lineWidth": 1,
            "pointSize": 1,
            "scaleDistribution": {
              "type": "linear"
            },
            "showPoints": "auto",
            "spanNulls": false,
            "stacking": {
              "group": "A",
              "mode": "none"
            },
            "thresholdsStyle": {
              "mode": "off"
            }
          },
          "mappings": [],
          "thresholds": {
            "mode": "absolute",
            "steps": [
              {
                "color": "green"
              },
              {
                "color": "red",
                "value": 80
              }
            ]
          }
        },
        "overrides": [
          {
            "matcher": {
              "id": "byName",
              "options": "Baseline Boguk ratio"
            },
            "properties": [
              {
                "id": "custom.lineStyle",
                "value": {
                  "dash": [
                    10,
                    10
                  ],
                  "fill": "dash"
                }
              },
              {
                "id": "color",
                "value": {
                  "fixedColor": "dark-red",
                  "mode": "fixed"
                }
              }
            ]
          },
          {
            "matcher": {
              "id": "byName",
              "options": "Boguk ratio"
            },
            "properties": [
              {
                "id": "color",
                "value": {
                  "fixedColor": "green",
                  "mode": "fixed"
                }
              }
            ]
          }
        ]
      },
      "gridPos": {
        "h": 18,
        "w": 24,
        "x": 0,
        "y": 0
      },
      "id": 1,
      "options": {
        "legend": {
          "calcs": [],
          "displayMode": "table",
          "placement": "bottom",
          "showLegend": true
        },
        "tooltip": {
          "hideZeros": false,
          "mode": "single",
          "sort": "none"
        }
      },
      "pluginVersion": "12.0.2",
      "targets": [
        {
          "datasource": {
            "type": "prometheus",
            "uid": "P7A0D6631BB10B34F"
          },
          "disableTextWrap": false,
          "editorMode": "code",
          "expr": "pgwatch_pg_class_total_relation_size_bytes{relname=\"$index_name\", schemaname=\"$schema_name\"} / pgwatch_pg_class_reltuples{relname=\"$index_name\", schemaname=\"$schema_name\"}",
          "fullMetaSearch": false,
          "includeNullMetadata": true,
          "interval": "",
          "legendFormat": "Current Boguk ratio",
          "range": true,
          "refId": "A",
          "useBackend": false
        },
        {
          "datasource": {
            "type": "prometheus",
            "uid": "P7A0D6631BB10B34F"
          },
          "editorMode": "code",
          "expr": "pgwatch_pg_index_pilot_best_ratio{indexrelname=\"$index_name\", schemaname=\"$schema_name\"}",
          "hide": false,
          "instant": false,
          "legendFormat": "Baseline Boguk ratio",
          "range": true,
          "refId": "B"
        }
      ],
      "title": "",
      "type": "timeseries"
    }
  ],
  "preload": false,
  "schemaVersion": 41,
  "tags": [],
  "templating": {
    "list": [
      {
        "current": {
          "text": "test_pilot",
          "value": "test_pilot"
        },
        "definition": "label_values(pgwatch_pg_index_pilot_estimated_tuples,schemaname)",
        "name": "schema_name",
        "options": [],
        "query": {
          "qryType": 1,
          "query": "label_values(pgwatch_pg_index_pilot_estimated_tuples,schemaname)",
          "refId": "PrometheusVariableQueryEditor-VariableQuery"
        },
        "refresh": 1,
        "regex": "",
        "type": "query"
      },
      {
        "current": {
          "text": "",
          "value": ""
        },
        "definition": "label_values(pgwatch_pg_index_pilot_estimated_tuples{schemaname=\"$schema_name\"},indexrelname)",
        "name": "index_name",
        "options": [],
        "query": {
          "qryType": 1,
          "query": "label_values(pgwatch_pg_index_pilot_estimated_tuples{schemaname=\"$schema_name\"},indexrelname)",
          "refId": "PrometheusVariableQueryEditor-VariableQuery"
        },
        "refresh": 1,
        "regex": "",
        "type": "query"
      }
    ]
  },
  "time": {
    "from": "now-1h",
    "to": "now"
  },
  "timepicker": {},
  "timezone": "browser",
  "title": "10. Single index analysis",
  "uid": "aa0128c5-c5a0-4418-a99e-c941af10426e",
  "version": 6
}