{
    "annotations": {
      "list": [
        {
          "builtIn": 1,
          "datasource": {
            "type": "grafana",
            "uid": "-- Grafana --"
          },
          "enable": true,
          "hide": true,
          "iconColor": "rgba(0, 211, 255, 1)",
          "name": "Annotations & Alerts",
          "type": "dashboard"
        }
      ]
    },
    "editable": true,
    "fiscalYearStartMonth": 0,
    "graphTooltip": 1,
    "id": 15,
    "links": [],
    "panels": [
      {
        "datasource": {
          "type": "prometheus",
          "uid": "P7A0D6631BB10B34F"
        },
        "fieldConfig": {
          "defaults": {
            "color": {
              "mode": "palette-classic"
            },
            "custom": {
              "axisBorderShow": false,
              "axisCenteredZero": false,
              "axisColorMode": "text",
              "axisLabel": "",
              "axisPlacement": "auto",
              "barAlignment": 0,
              "barWidthFactor": 0.6,
              "drawStyle": "line",
              "fillOpacity": 0,
              "gradientMode": "none",
              "hideFrom": {
                "legend": false,
                "tooltip": false,
                "viz": false
              },
              "insertNulls": false,
              "lineInterpolation": "linear",
              "lineWidth": 1,
              "pointSize": 1,
              "scaleDistribution": {
                "type": "linear"
              },
              "showPoints": "auto",
              "spanNulls": true,
              "stacking": {
                "group": "A",
                "mode": "none"
              },
              "thresholdsStyle": {
                "mode": "off"
              }
            },
            "mappings": [],
            "thresholds": {
              "mode": "absolute",
              "steps": [
                {
                  "color": "green"
                },
                {
                  "color": "red",
                  "value": 80
                }
              ]
            },
            "unit": "bytes"
          },
          "overrides": []
        },
        "gridPos": {
          "h": 13,
          "w": 12,
          "x": 0,
          "y": 0
        },
        "id": 1,
        "options": {
          "legend": {
            "calcs": [
              "last"
            ],
            "displayMode": "table",
            "placement": "bottom",
            "showLegend": true,
            "sortBy": "Last",
            "sortDesc": true
          },
          "tooltip": {
            "hideZeros": false,
            "mode": "single",
            "sort": "none"
          }
        },
        "pluginVersion": "12.0.2",
        "targets": [
          {
            "disableTextWrap": false,
            "editorMode": "code",
            "expr": "topk($top_n, pgwatch_pg_class_total_relation_size_bytes{relkind=\"114\", schemaname=~\"$schema_name\", datname=\"$db_name\", cluster=\"$cluster_name\", node_name=\"$node_name\"})",
            "fullMetaSearch": false,
            "includeNullMetadata": true,
            "legendFormat": "{{schemaname}}.{{relname}}",
            "range": true,
            "refId": "A",
            "useBackend": false
          }
        ],
        "title": "Top $top_n tables by size",
        "type": "timeseries"
      },
      {
        "datasource": {
          "type": "prometheus",
          "uid": "P7A0D6631BB10B34F"
        },
        "fieldConfig": {
          "defaults": {
            "color": {
              "mode": "palette-classic"
            },
            "custom": {
              "axisBorderShow": false,
              "axisCenteredZero": false,
              "axisColorMode": "text",
              "axisLabel": "",
              "axisPlacement": "auto",
              "barAlignment": 0,
              "barWidthFactor": 0.6,
              "drawStyle": "line",
              "fillOpacity": 0,
              "gradientMode": "none",
              "hideFrom": {
                "legend": false,
                "tooltip": false,
                "viz": false
              },
              "insertNulls": false,
              "lineInterpolation": "linear",
              "lineWidth": 1,
              "pointSize": 1,
              "scaleDistribution": {
                "type": "linear"
              },
              "showPoints": "auto",
              "spanNulls": true,
              "stacking": {
                "group": "A",
                "mode": "none"
              },
              "thresholdsStyle": {
                "mode": "off"
              }
            },
            "mappings": [],
            "thresholds": {
              "mode": "absolute",
              "steps": [
                {
                  "color": "green"
                },
                {
                  "color": "red",
                  "value": 80
                }
              ]
            },
            "unit": "Bps"
          },
          "overrides": []
        },
        "gridPos": {
          "h": 13,
          "w": 12,
          "x": 12,
          "y": 0
        },
        "id": 7,
        "options": {
          "legend": {
            "calcs": [
              "last"
            ],
            "displayMode": "table",
            "placement": "bottom",
            "showLegend": true,
            "sortBy": "Last",
            "sortDesc": true
          },
          "tooltip": {
            "hideZeros": false,
            "mode": "single",
            "sort": "none"
          }
        },
        "pluginVersion": "12.0.2",
        "targets": [
          {
            "disableTextWrap": false,
            "editorMode": "code",
            "expr": "topk($top_n, irate(pgwatch_pg_class_total_relation_size_bytes{relkind=\"114\", schemaname=~\"$schema_name\", datname=\"$db_name\", cluster=\"$cluster_name\", node_name=\"$node_name\"}[$__rate_interval]))",
            "fullMetaSearch": false,
            "includeNullMetadata": true,
            "interval": "20",
            "legendFormat": "{{schemaname}}.{{relname}}",
            "range": true,
            "refId": "A",
            "useBackend": false
          }
        ],
        "title": "Top $top_n tables by size change rate",
        "type": "timeseries"
      },
      {
        "datasource": {
          "type": "prometheus",
          "uid": "P7A0D6631BB10B34F"
        },
        "fieldConfig": {
          "defaults": {
            "color": {
              "mode": "palette-classic"
            },
            "custom": {
              "axisBorderShow": false,
              "axisCenteredZero": false,
              "axisColorMode": "text",
              "axisLabel": "",
              "axisPlacement": "auto",
              "barAlignment": 0,
              "barWidthFactor": 0.6,
              "drawStyle": "line",
              "fillOpacity": 0,
              "gradientMode": "none",
              "hideFrom": {
                "legend": false,
                "tooltip": false,
                "viz": false
              },
              "insertNulls": false,
              "lineInterpolation": "linear",
              "lineWidth": 1,
              "pointSize": 1,
              "scaleDistribution": {
                "type": "linear"
              },
              "showPoints": "auto",
              "spanNulls": true,
              "stacking": {
                "group": "A",
                "mode": "none"
              },
              "thresholdsStyle": {
                "mode": "off"
              }
            },
            "mappings": [],
            "thresholds": {
              "mode": "absolute",
              "steps": [
                {
                  "color": "green"
                },
                {
                  "color": "red",
                  "value": 80
                }
              ]
            },
            "unit": "percent"
          },
          "overrides": []
        },
        "gridPos": {
          "h": 13,
          "w": 12,
          "x": 0,
          "y": 13
        },
        "id": 8,
        "options": {
          "legend": {
            "calcs": [
              "min",
              "max",
              "mean"
            ],
            "displayMode": "table",
            "placement": "bottom",
            "showLegend": true,
            "sortBy": "Mean",
            "sortDesc": true
          },
          "tooltip": {
            "hideZeros": false,
            "mode": "single",
            "sort": "none"
          }
        },
        "pluginVersion": "12.0.2",
        "targets": [
          {
            "disableTextWrap": false,
            "editorMode": "code",
            "expr": "topk($top_n, pgwatch_pg_table_bloat_bloat_pct{schemaname=~\"$schema_name\", datname=\"$db_name\", cluster=\"$cluster_name\", node_name=\"$node_name\"})",
            "fullMetaSearch": false,
            "includeNullMetadata": true,
            "legendFormat": "{{schemaname}}.{{tblname}}",
            "range": true,
            "refId": "A",
            "useBackend": false
          }
        ],
        "title": "Top $top_n tables by bloat %",
        "type": "timeseries"
      },
      {
        "datasource": {
          "type": "prometheus",
          "uid": "P7A0D6631BB10B34F"
        },
        "fieldConfig": {
          "defaults": {
            "color": {
              "mode": "palette-classic"
            },
            "custom": {
              "axisBorderShow": false,
              "axisCenteredZero": false,
              "axisColorMode": "text",
              "axisLabel": "",
              "axisPlacement": "auto",
              "barAlignment": 0,
              "barWidthFactor": 0.6,
              "drawStyle": "line",
              "fillOpacity": 0,
              "gradientMode": "none",
              "hideFrom": {
                "legend": false,
                "tooltip": false,
                "viz": false
              },
              "insertNulls": false,
              "lineInterpolation": "linear",
              "lineWidth": 1,
              "pointSize": 1,
              "scaleDistribution": {
                "type": "linear"
              },
              "showPoints": "auto",
              "spanNulls": true,
              "stacking": {
                "group": "A",
                "mode": "none"
              },
              "thresholdsStyle": {
                "mode": "off"
              }
            },
            "mappings": [],
            "thresholds": {
              "mode": "absolute",
              "steps": [
                {
                  "color": "green"
                },
                {
                  "color": "red",
                  "value": 80
                }
              ]
            },
            "unit": "bytes"
          },
          "overrides": []
        },
        "gridPos": {
          "h": 13,
          "w": 12,
          "x": 12,
          "y": 13
        },
        "id": 2,
        "options": {
          "legend": {
            "calcs": [
              "last"
            ],
            "displayMode": "table",
            "placement": "bottom",
            "showLegend": true,
            "sortBy": "Last",
            "sortDesc": true
          },
          "tooltip": {
            "hideZeros": false,
            "mode": "single",
            "sort": "none"
          }
        },
        "pluginVersion": "12.0.2",
        "targets": [
          {
            "disableTextWrap": false,
            "editorMode": "code",
            "expr": "topk($top_n, pgwatch_pg_table_bloat_bloat_size{schemaname=~\"$schema_name\", datname=\"$db_name\", cluster=\"$cluster_name\", node_name=\"$node_name\"})",
            "fullMetaSearch": false,
            "includeNullMetadata": true,
            "legendFormat": "{{schemaname}}.{{tblname}}",
            "range": true,
            "refId": "A",
            "useBackend": false
          }
        ],
        "title": "Top $top_n tables by bloat size",
        "type": "timeseries"
      },
      {
        "collapsed": false,
        "gridPos": {
          "h": 1,
          "w": 24,
          "x": 0,
          "y": 26
        },
        "id": 11,
        "panels": [],
        "title": "Tuple stats",
        "type": "row"
      },
      {
        "datasource": {
          "type": "prometheus",
          "uid": "P7A0D6631BB10B34F"
        },
        "fieldConfig": {
          "defaults": {
            "color": {
              "mode": "palette-classic"
            },
            "custom": {
              "axisBorderShow": false,
              "axisCenteredZero": false,
              "axisColorMode": "text",
              "axisLabel": "",
              "axisPlacement": "auto",
              "barAlignment": 0,
              "barWidthFactor": 0.6,
              "drawStyle": "line",
              "fillOpacity": 100,
              "gradientMode": "none",
              "hideFrom": {
                "legend": false,
                "tooltip": false,
                "viz": false
              },
              "insertNulls": false,
              "lineInterpolation": "linear",
              "lineWidth": 1,
              "pointSize": 1,
              "scaleDistribution": {
                "type": "linear"
              },
              "showPoints": "auto",
              "spanNulls": false,
              "stacking": {
                "group": "A",
                "mode": "normal"
              },
              "thresholdsStyle": {
                "mode": "off"
              }
            },
            "mappings": [],
            "thresholds": {
              "mode": "absolute",
              "steps": [
                {
                  "color": "green"
                },
                {
                  "color": "red",
                  "value": 80
                }
              ]
            },
            "unit": "ops"
          },
          "overrides": [
            {
              "matcher": {
                "id": "byFrameRefID",
                "options": "A"
              },
              "properties": [
                {
                  "id": "color",
                  "value": {
                    "fixedColor": "dark-green",
                    "mode": "fixed"
                  }
                }
              ]
            },
            {
              "matcher": {
                "id": "byFrameRefID",
                "options": "B"
              },
              "properties": [
                {
                  "id": "color",
                  "value": {
                    "fixedColor": "orange",
                    "mode": "fixed"
                  }
                }
              ]
            },
            {
              "matcher": {
                "id": "byFrameRefID",
                "options": "C"
              },
              "properties": [
                {
                  "id": "color",
                  "value": {
                    "fixedColor": "yellow",
                    "mode": "fixed"
                  }
                }
              ]
            },
            {
              "matcher": {
                "id": "byFrameRefID",
                "options": "D"
              },
              "properties": [
                {
                  "id": "color",
                  "value": {
                    "fixedColor": "dark-red",
                    "mode": "fixed"
                  }
                }
              ]
            }
          ]
        },
        "gridPos": {
          "h": 10,
          "w": 24,
          "x": 0,
          "y": 27
        },
        "id": 12,
        "options": {
          "legend": {
            "calcs": [
              "min",
              "max",
              "mean"
            ],
            "displayMode": "table",
            "placement": "bottom",
            "showLegend": true,
            "sortBy": "Max",
            "sortDesc": true
          },
          "tooltip": {
            "hideZeros": false,
            "mode": "single",
            "sort": "none"
          }
        },
        "pluginVersion": "12.0.2",
        "targets": [
          {
            "datasource": {
              "type": "prometheus",
              "uid": "P7A0D6631BB10B34F"
            },
            "disableTextWrap": false,
            "editorMode": "code",
            "expr": "sum(irate(pgwatch_table_stats_n_tup_ins{datname=\"$db_name\", cluster=\"$cluster_name\", node_name=\"$node_name\", schema=~\"$schema_name\"}[$__rate_interval]))",
            "fullMetaSearch": false,
            "includeNullMetadata": true,
            "interval": "60",
            "legendFormat": "Inserts",
            "range": true,
            "refId": "A",
            "useBackend": false
          },
          {
            "datasource": {
              "type": "prometheus",
              "uid": "P7A0D6631BB10B34F"
            },
            "disableTextWrap": false,
            "editorMode": "code",
            "expr": "sum(irate(pgwatch_table_stats_n_tup_upd{datname=\"$db_name\", cluster=\"$cluster_name\", node_name=\"$node_name\", schema=~\"$schema_name\"}[$__rate_interval]))",
            "fullMetaSearch": false,
            "hide": false,
            "includeNullMetadata": true,
            "interval": "60",
            "legendFormat": "Updates",
            "range": true,
            "refId": "B",
            "useBackend": false
          },
          {
            "datasource": {
              "type": "prometheus",
              "uid": "P7A0D6631BB10B34F"
            },
            "disableTextWrap": false,
            "editorMode": "code",
            "expr": "sum(irate(pgwatch_table_stats_n_tup_hot_upd{datname=\"$db_name\", cluster=\"$cluster_name\", node_name=\"$node_name\", schema=~\"$schema_name\"}[$__rate_interval]))",
            "fullMetaSearch": false,
            "hide": false,
            "includeNullMetadata": true,
            "interval": "60",
            "legendFormat": "HOT Updates",
            "range": true,
            "refId": "C",
            "useBackend": false
          },
          {
            "datasource": {
              "type": "prometheus",
              "uid": "P7A0D6631BB10B34F"
            },
            "disableTextWrap": false,
            "editorMode": "code",
            "expr": "sum(irate(pgwatch_table_stats_n_tup_del{datname=\"$db_name\", cluster=\"$cluster_name\", node_name=\"$node_name\", schema=~\"$schema_name\"}[$__rate_interval]))",
            "fullMetaSearch": false,
            "hide": false,
            "includeNullMetadata": true,
            "interval": "60",
            "legendFormat": "Deletes",
            "range": true,
            "refId": "D",
            "useBackend": false
          }
        ],
        "title": "Tuple operations (aggregated)",
        "transformations": [
          {
            "id": "calculateField",
            "options": {
              "alias": "Non-HOT Updates",
              "binary": {
                "left": {
                  "matcher": {
                    "id": "byName",
                    "options": "Updates"
                  }
                },
                "operator": "-",
                "right": {
                  "matcher": {
                    "id": "byName",
                    "options": "HOT Updates"
                  }
                }
              },
              "mode": "binary",
              "reduce": {
                "reducer": "sum"
              }
            }
          },
          {
            "id": "organize",
            "options": {
              "excludeByName": {
                "Updates": true
              },
              "includeByName": {},
              "indexByName": {},
              "renameByName": {
                "Hot Updates": "HOT Updates"
              }
            }
          }
        ],
        "type": "timeseries"
      },
      {
        "datasource": {
          "type": "prometheus",
          "uid": "P7A0D6631BB10B34F"
        },
        "fieldConfig": {
          "defaults": {
            "color": {
              "mode": "palette-classic"
            },
            "custom": {
              "axisBorderShow": false,
              "axisCenteredZero": false,
              "axisColorMode": "text",
              "axisLabel": "",
              "axisPlacement": "auto",
              "barAlignment": 0,
              "barWidthFactor": 0.6,
              "drawStyle": "line",
              "fillOpacity": 100,
              "gradientMode": "none",
              "hideFrom": {
                "legend": false,
                "tooltip": false,
                "viz": false
              },
              "insertNulls": false,
              "lineInterpolation": "linear",
              "lineWidth": 1,
              "pointSize": 1,
              "scaleDistribution": {
                "type": "linear"
              },
              "showPoints": "auto",
              "spanNulls": false,
              "stacking": {
                "group": "A",
                "mode": "normal"
              },
              "thresholdsStyle": {
                "mode": "off"
              }
            },
            "mappings": [],
            "thresholds": {
              "mode": "absolute",
              "steps": [
                {
                  "color": "green"
                },
                {
                  "color": "red",
                  "value": 80
                }
              ]
            },
            "unit": "percentunit"
          },
          "overrides": [
            {
              "matcher": {
                "id": "byFrameRefID",
                "options": "A"
              },
              "properties": [
                {
                  "id": "color",
                  "value": {
                    "fixedColor": "dark-green",
                    "mode": "fixed"
                  }
                }
              ]
            },
            {
              "matcher": {
                "id": "byFrameRefID",
                "options": "B"
              },
              "properties": [
                {
                  "id": "color",
                  "value": {
                    "fixedColor": "orange",
                    "mode": "fixed"
                  }
                }
              ]
            },
            {
              "matcher": {
                "id": "byFrameRefID",
                "options": "C"
              },
              "properties": [
                {
                  "id": "color",
                  "value": {
                    "fixedColor": "yellow",
                    "mode": "fixed"
                  }
                }
              ]
            },
            {
              "matcher": {
                "id": "byFrameRefID",
                "options": "D"
              },
              "properties": [
                {
                  "id": "color",
                  "value": {
                    "fixedColor": "dark-red",
                    "mode": "fixed"
                  }
                }
              ]
            }
          ]
        },
        "gridPos": {
          "h": 10,
          "w": 24,
          "x": 0,
          "y": 37
        },
        "id": 21,
        "options": {
          "legend": {
            "calcs": [
              "min",
              "max",
              "mean"
            ],
            "displayMode": "table",
            "placement": "bottom",
            "showLegend": true,
            "sortBy": "Max",
            "sortDesc": true
          },
          "tooltip": {
            "hideZeros": false,
            "mode": "single",
            "sort": "none"
          }
        },
        "pluginVersion": "12.0.2",
        "targets": [
          {
            "datasource": {
              "type": "prometheus",
              "uid": "P7A0D6631BB10B34F"
            },
            "disableTextWrap": false,
            "editorMode": "code",
            "expr": "sum(irate(pgwatch_table_stats_n_tup_ins{datname=\"$db_name\", cluster=\"$cluster_name\", node_name=\"$node_name\", schema=~\"$schema_name\"}[$__rate_interval]))",
            "fullMetaSearch": false,
            "includeNullMetadata": true,
            "interval": "60",
            "legendFormat": "Inserts",
            "range": true,
            "refId": "A",
            "useBackend": false
          },
          {
            "datasource": {
              "type": "prometheus",
              "uid": "P7A0D6631BB10B34F"
            },
            "disableTextWrap": false,
            "editorMode": "code",
            "expr": "sum(irate(pgwatch_table_stats_n_tup_upd{datname=\"$db_name\", cluster=\"$cluster_name\", node_name=\"$node_name\", schema=~\"$schema_name\"}[$__rate_interval]))",
            "fullMetaSearch": false,
            "hide": false,
            "includeNullMetadata": true,
            "interval": "60",
            "legendFormat": "Updates",
            "range": true,
            "refId": "B",
            "useBackend": false
          },
          {
            "datasource": {
              "type": "prometheus",
              "uid": "P7A0D6631BB10B34F"
            },
            "disableTextWrap": false,
            "editorMode": "code",
            "expr": "sum(irate(pgwatch_table_stats_n_tup_hot_upd{datname=\"$db_name\", cluster=\"$cluster_name\", node_name=\"$node_name\", schema=~\"$schema_name\"}[$__rate_interval]))",
            "fullMetaSearch": false,
            "hide": false,
            "includeNullMetadata": true,
            "interval": "60",
            "legendFormat": "HOT Updates",
            "range": true,
            "refId": "C",
            "useBackend": false
          },
          {
            "datasource": {
              "type": "prometheus",
              "uid": "P7A0D6631BB10B34F"
            },
            "disableTextWrap": false,
            "editorMode": "code",
            "expr": "sum(irate(pgwatch_table_stats_n_tup_del{datname=\"$db_name\", cluster=\"$cluster_name\", node_name=\"$node_name\", schema=~\"$schema_name\"}[$__rate_interval]))",
            "fullMetaSearch": false,
            "hide": false,
            "includeNullMetadata": true,
            "interval": "60",
            "legendFormat": "Deletes",
            "range": true,
            "refId": "D",
            "useBackend": false
          }
        ],
        "title": "Tuple operations (%) (Aggregated)",
        "transformations": [
          {
            "id": "calculateField",
            "options": {
              "alias": "Non-HOT Updates",
              "binary": {
                "left": {
                  "matcher": {
                    "id": "byName",
                    "options": "Updates"
                  }
                },
                "operator": "-",
                "right": {
                  "matcher": {
                    "id": "byName",
                    "options": "HOT Updates"
                  }
                }
              },
              "mode": "binary",
              "reduce": {
                "reducer": "sum"
              }
            }
          },
          {
            "id": "calculateField",
            "options": {
              "mode": "reduceRow",
              "reduce": {
                "include": [
                  "Inserts",
                  "Deletes",
                  "Updates"
                ],
                "reducer": "sum"
              }
            }
          },
          {
            "id": "calculateField",
            "options": {
              "alias": "Inserts %",
              "binary": {
                "left": {
                  "matcher": {
                    "id": "byName",
                    "options": "Inserts"
                  }
                },
                "operator": "/",
                "right": {
                  "matcher": {
                    "id": "byName",
                    "options": "Total"
                  }
                }
              },
              "mode": "binary",
              "reduce": {
                "reducer": "sum"
              }
            }
          },
          {
            "id": "calculateField",
            "options": {
              "alias": "Non-HOT-Updates %",
              "binary": {
                "left": {
                  "matcher": {
                    "id": "byName",
                    "options": "Non-HOT Updates"
                  }
                },
                "operator": "/",
                "right": {
                  "matcher": {
                    "id": "byName",
                    "options": "Total"
                  }
                }
              },
              "mode": "binary",
              "reduce": {
                "reducer": "sum"
              }
            }
          },
          {
            "id": "calculateField",
            "options": {
              "alias": "HOT-Updates",
              "binary": {
                "left": {
                  "matcher": {
                    "id": "byName",
                    "options": "HOT Updates"
                  }
                },
                "operator": "/",
                "right": {
                  "matcher": {
                    "id": "byName",
                    "options": "Total"
                  }
                }
              },
              "mode": "binary",
              "reduce": {
                "reducer": "sum"
              }
            }
          },
          {
            "id": "calculateField",
            "options": {
              "alias": "Deletes %",
              "binary": {
                "left": {
                  "matcher": {
                    "id": "byName",
                    "options": "Deletes"
                  }
                },
                "operator": "/",
                "right": {
                  "matcher": {
                    "id": "byName",
                    "options": "Total"
                  }
                }
              },
              "mode": "binary",
              "reduce": {
                "reducer": "sum"
              }
            }
          },
          {
            "id": "organize",
            "options": {
              "excludeByName": {
                "Deletes": true,
                "HOT Updates": true,
                "Inserts": true,
                "Non-HOT Updates": true,
                "Total": true,
                "Updates": true
              },
              "includeByName": {},
              "indexByName": {},
              "renameByName": {
                "Hot Updates": "HOT Updates"
              }
            }
          }
        ],
        "type": "timeseries"
      },
      {
        "fieldConfig": {
          "defaults": {
            "color": {
              "mode": "palette-classic"
            },
            "custom": {
              "axisBorderShow": false,
              "axisCenteredZero": false,
              "axisColorMode": "text",
              "axisLabel": "",
              "axisPlacement": "auto",
              "barAlignment": 0,
              "barWidthFactor": 0.6,
              "drawStyle": "line",
              "fillOpacity": 0,
              "gradientMode": "none",
              "hideFrom": {
                "legend": false,
                "tooltip": false,
                "viz": false
              },
              "insertNulls": false,
              "lineInterpolation": "linear",
              "lineWidth": 1,
              "pointSize": 5,
              "scaleDistribution": {
                "type": "linear"
              },
              "showPoints": "auto",
              "spanNulls": false,
              "stacking": {
                "group": "A",
                "mode": "none"
              },
              "thresholdsStyle": {
                "mode": "off"
              }
            },
            "mappings": [],
            "thresholds": {
              "mode": "absolute",
              "steps": [
                {
                  "color": "green"
                },
                {
                  "color": "red",
                  "value": 80
                }
              ]
            }
          },
          "overrides": []
        },
        "gridPos": {
          "h": 10,
          "w": 12,
          "x": 0,
          "y": 47
        },
        "id": 3,
        "options": {
          "legend": {
            "calcs": [
              "min",
              "max",
              "mean"
            ],
            "displayMode": "table",
            "placement": "bottom",
            "showLegend": true,
            "sortBy": "Mean",
            "sortDesc": true
          },
          "tooltip": {
            "hideZeros": false,
            "mode": "single",
            "sort": "none"
          }
        },
        "pluginVersion": "12.0.2",
        "targets": [
          {
            "datasource": {
              "type": "prometheus",
              "uid": "P7A0D6631BB10B34F"
            },
            "disableTextWrap": false,
            "editorMode": "code",
            "expr": "topk($top_n, sum by(schema, table_name, table_full_name) (irate(pgwatch_table_stats_n_tup_ins{datname=\"$db_name\", cluster=\"$cluster_name\", node_name=\"$node_name\", schema=~\"$schema_name\"}[$__rate_interval])))",
            "fullMetaSearch": false,
            "includeNullMetadata": true,
            "interval": "60",
            "legendFormat": "{{table_full_name}}",
            "range": true,
            "refId": "A",
            "useBackend": false
          }
        ],
        "title": "Top $top_n tables by inserts/sec",
        "type": "timeseries"
      },
      {
        "datasource": {
          "type": "prometheus",
          "uid": "P7A0D6631BB10B34F"
        },
        "fieldConfig": {
          "defaults": {
            "color": {
              "mode": "palette-classic"
            },
            "custom": {
              "axisBorderShow": false,
              "axisCenteredZero": false,
              "axisColorMode": "text",
              "axisLabel": "",
              "axisPlacement": "auto",
              "barAlignment": 0,
              "barWidthFactor": 0.6,
              "drawStyle": "line",
              "fillOpacity": 0,
              "gradientMode": "none",
              "hideFrom": {
                "legend": false,
                "tooltip": false,
                "viz": false
              },
              "insertNulls": false,
              "lineInterpolation": "linear",
              "lineWidth": 1,
              "pointSize": 1,
              "scaleDistribution": {
                "type": "linear"
              },
              "showPoints": "auto",
              "spanNulls": false,
              "stacking": {
                "group": "A",
                "mode": "none"
              },
              "thresholdsStyle": {
                "mode": "off"
              }
            },
            "links": [
              {
                "title": "Table details",
                "url": "/d/11-single-table-analysis/11-single-table-analysis?orgId=1&var-cluster_name=${cluster_name}&var-node_name=${node_name}&var-db_name=${db_name}&var-schema_name=${__field.labels.schema}&var-table_name=${__field.labels.table_name}"
              }
            ],
            "mappings": [],
            "thresholds": {
              "mode": "absolute",
              "steps": [
                {
                  "color": "green"
                },
                {
                  "color": "red",
                  "value": 80
                }
              ]
            },
            "unit": "ops"
          },
          "overrides": []
        },
        "gridPos": {
          "h": 10,
          "w": 12,
          "x": 12,
          "y": 47
        },
        "id": 4,
        "options": {
          "legend": {
            "calcs": [
              "min",
              "max",
              "mean"
            ],
            "displayMode": "table",
            "placement": "bottom",
            "showLegend": true,
            "sortBy": "Mean",
            "sortDesc": true
          },
          "tooltip": {
            "hideZeros": false,
            "mode": "single",
            "sort": "none"
          }
        },
        "pluginVersion": "12.0.2",
        "targets": [
          {
            "datasource": {
              "type": "prometheus",
              "uid": "P7A0D6631BB10B34F"
            },
            "disableTextWrap": false,
            "editorMode": "code",
            "expr": "topk($top_n, sum by(schema, table_name, table_full_name) (irate(pgwatch_table_stats_n_tup_upd{datname=\"$db_name\", cluster=\"$cluster_name\", node_name=\"$node_name\", schema=~\"$schema_name\"}[$__rate_interval])))",
            "fullMetaSearch": false,
            "includeNullMetadata": true,
            "interval": "60",
            "legendFormat": "{{table_full_name}}",
            "range": true,
            "refId": "A",
            "useBackend": false
          }
        ],
        "title": "Top $top_n tables by updates/sec",
        "type": "timeseries"
      },
      {
        "datasource": {
          "type": "prometheus",
          "uid": "P7A0D6631BB10B34F"
        },
        "fieldConfig": {
          "defaults": {
            "color": {
              "mode": "palette-classic"
            },
            "custom": {
              "axisBorderShow": false,
              "axisCenteredZero": false,
              "axisColorMode": "text",
              "axisLabel": "",
              "axisPlacement": "auto",
              "barAlignment": 0,
              "barWidthFactor": 0.6,
              "drawStyle": "line",
              "fillOpacity": 0,
              "gradientMode": "none",
              "hideFrom": {
                "legend": false,
                "tooltip": false,
                "viz": false
              },
              "insertNulls": false,
              "lineInterpolation": "linear",
              "lineWidth": 1,
              "pointSize": 1,
              "scaleDistribution": {
                "type": "linear"
              },
              "showPoints": "auto",
              "spanNulls": false,
              "stacking": {
                "group": "A",
                "mode": "none"
              },
              "thresholdsStyle": {
                "mode": "off"
              }
            },
            "links": [
              {
                "title": "Table details",
                "url": "/d/11-single-table-analysis/11-single-table-analysis?orgId=1&var-cluster_name=${cluster_name}&var-node_name=${node_name}&var-db_name=${db_name}&var-schema_name=${__field.labels.schema}&var-table_name=${__field.labels.table_name}"
              }
            ],
            "mappings": [],
            "thresholds": {
              "mode": "absolute",
              "steps": [
                {
                  "color": "green"
                },
                {
                  "color": "red",
                  "value": 80
                }
              ]
            },
            "unit": "ops"
          },
          "overrides": []
        },
        "gridPos": {
          "h": 10,
          "w": 12,
          "x": 0,
          "y": 57
        },
        "id": 5,
        "options": {
          "legend": {
            "calcs": [
              "min",
              "max",
              "mean"
            ],
            "displayMode": "table",
            "placement": "bottom",
            "showLegend": true,
            "sortBy": "Mean",
            "sortDesc": true
          },
          "tooltip": {
            "hideZeros": false,
            "mode": "single",
            "sort": "none"
          }
        },
        "pluginVersion": "12.0.2",
        "targets": [
          {
            "datasource": {
              "type": "prometheus",
              "uid": "P7A0D6631BB10B34F"
            },
            "disableTextWrap": false,
            "editorMode": "code",
            "expr": "topk($top_n, sum by(schema, table_name, table_full_name) (irate(pgwatch_table_stats_n_tup_del{datname=\"$db_name\", cluster=\"$cluster_name\", node_name=\"$node_name\", schema=~\"$schema_name\"}[$__rate_interval])))",
            "fullMetaSearch": false,
            "includeNullMetadata": true,
            "interval": "60",
            "legendFormat": "{{table_full_name}}",
            "range": true,
            "refId": "A",
            "useBackend": false
          }
        ],
        "title": "Top $top_n tables by deletes/sec",
        "type": "timeseries"
      },
      {
        "datasource": {
          "type": "prometheus",
          "uid": "P7A0D6631BB10B34F"
        },
        "fieldConfig": {
          "defaults": {
            "color": {
              "mode": "palette-classic"
            },
            "custom": {
              "axisBorderShow": false,
              "axisCenteredZero": false,
              "axisColorMode": "text",
              "axisLabel": "",
              "axisPlacement": "auto",
              "barAlignment": 0,
              "barWidthFactor": 0.6,
              "drawStyle": "line",
              "fillOpacity": 0,
              "gradientMode": "none",
              "hideFrom": {
                "legend": false,
                "tooltip": false,
                "viz": false
              },
              "insertNulls": false,
              "lineInterpolation": "linear",
              "lineWidth": 1,
              "pointSize": 1,
              "scaleDistribution": {
                "type": "linear"
              },
              "showPoints": "auto",
              "spanNulls": false,
              "stacking": {
                "group": "A",
                "mode": "none"
              },
              "thresholdsStyle": {
                "mode": "off"
              }
            },
            "links": [
              {
                "title": "Table details",
                "url": "/d/11-single-table-analysis/11-single-table-analysis?orgId=1&var-cluster_name=${cluster_name}&var-node_name=${node_name}&var-db_name=${db_name}&var-schema_name=${__field.labels.schema}&var-table_name=${__field.labels.table_name}"
              }
            ],
            "mappings": [],
            "thresholds": {
              "mode": "absolute",
              "steps": [
                {
                  "color": "green"
                },
                {
                  "color": "red",
                  "value": 80
                }
              ]
            },
            "unit": "ops"
          },
          "overrides": []
        },
        "gridPos": {
          "h": 10,
          "w": 12,
          "x": 12,
          "y": 57
        },
        "id": 6,
        "options": {
          "legend": {
            "calcs": [
              "min",
              "max",
              "mean"
            ],
            "displayMode": "table",
            "placement": "bottom",
            "showLegend": true,
            "sortBy": "Mean",
            "sortDesc": true
          },
          "tooltip": {
            "hideZeros": false,
            "mode": "single",
            "sort": "none"
          }
        },
        "pluginVersion": "12.0.2",
        "targets": [
          {
            "datasource": {
              "type": "prometheus",
              "uid": "P7A0D6631BB10B34F"
            },
            "disableTextWrap": false,
            "editorMode": "code",
            "expr": "topk($top_n, sum by(schema, table_name, table_full_name) (irate(pgwatch_table_stats_n_tup_hot_upd{datname=\"$db_name\", cluster=\"$cluster_name\", node_name=\"$node_name\", schema=~\"$schema_name\"}[$__rate_interval])))",
            "fullMetaSearch": false,
            "includeNullMetadata": true,
            "interval": "60",
            "legendFormat": "{{table_full_name}}",
            "range": true,
            "refId": "A",
            "useBackend": false
          }
        ],
        "title": "Top $top_n tables by HOT updates/sec",
        "type": "timeseries"
      },
      {
        "datasource": {
          "type": "prometheus",
          "uid": "P7A0D6631BB10B34F"
        },
        "fieldConfig": {
          "defaults": {
            "color": {
              "mode": "palette-classic"
            },
            "custom": {
              "axisBorderShow": false,
              "axisCenteredZero": false,
              "axisColorMode": "text",
              "axisLabel": "",
              "axisPlacement": "auto",
              "barAlignment": 0,
              "barWidthFactor": 0.6,
              "drawStyle": "line",
              "fillOpacity": 0,
              "gradientMode": "none",
              "hideFrom": {
                "legend": false,
                "tooltip": false,
                "viz": false
              },
              "insertNulls": false,
              "lineInterpolation": "linear",
              "lineWidth": 1,
              "pointSize": 1,
              "scaleDistribution": {
                "type": "linear"
              },
              "showPoints": "auto",
              "spanNulls": false,
              "stacking": {
                "group": "A",
                "mode": "none"
              },
              "thresholdsStyle": {
                "mode": "off"
              }
            },
            "links": [
              {
                "title": "Table details",
                "url": "/d/11-single-table-analysis/11-single-table-analysis?orgId=1&var-cluster_name=${cluster_name}&var-node_name=${node_name}&var-db_name=${db_name}&var-schema_name=${__field.labels.schema}&var-table_name=${__field.labels.table_name}"
              }
            ],
            "mappings": [],
            "thresholds": {
              "mode": "absolute",
              "steps": [
                {
                  "color": "green"
                },
                {
                  "color": "red",
                  "value": 80
                }
              ]
            },
            "unit": "ops"
          },
          "overrides": []
        },
        "gridPos": {
          "h": 10,
          "w": 12,
          "x": 0,
          "y": 67
        },
        "id": 10,
        "options": {
          "legend": {
            "calcs": [
              "min",
              "max",
              "mean"
            ],
            "displayMode": "table",
            "placement": "bottom",
            "showLegend": true,
            "sortBy": "Mean",
            "sortDesc": true
          },
          "tooltip": {
            "hideZeros": false,
            "mode": "single",
            "sort": "none"
          }
        },
        "pluginVersion": "12.0.2",
        "targets": [
          {
            "datasource": {
              "type": "prometheus",
              "uid": "P7A0D6631BB10B34F"
            },
            "disableTextWrap": false,
            "editorMode": "code",
            "expr": "topk($top_n, sum by(schema, table_name, table_full_name) (irate(pgwatch_table_stats_n_tup_upd{datname=\"$db_name\", cluster=\"$cluster_name\", node_name=\"$node_name\", schema=~\"$schema_name\"}[$__rate_interval]) - irate(pgwatch_table_stats_n_tup_hot_upd{datname=\"$db_name\", cluster=\"$cluster_name\", node_name=\"$node_name\", schema=~\"$schema_name\"}[$__rate_interval])))",
            "fullMetaSearch": false,
            "includeNullMetadata": true,
            "interval": "60",
            "legendFormat": "{{table_full_name}}",
            "range": true,
            "refId": "A",
            "useBackend": false
          }
        ],
        "title": "Top $top_n tables by Non-HOT updates/sec",
        "type": "timeseries"
      },
      {
        "fieldConfig": {
          "defaults": {},
          "overrides": []
        },
        "gridPos": {
          "h": 3,
          "w": 24,
          "x": 0,
          "y": 77
        },
        "id": 20,
        "options": {
          "code": {
            "language": "plaintext",
            "showLineNumbers": false,
            "showMiniMap": false
          },
          "content": "<h1>\n  Brought to you by <a href=\"https://postgres.ai\">Postgres AI</a>\n  <img src=\"https://postgres.ai/img/logo.svg\" alt=\"Postgres.AI\" style=\"height: 2em; vertical-align: middle; margin-left: 0.3em;\">\n</h1>\n",
          "mode": "html"
        },
        "pluginVersion": "12.0.2",
        "title": "",
        "type": "text"
      }
    ],
    "preload": false,
    "schemaVersion": 41,
    "tags": [],
    "templating": {
      "list": [
        {
          "current": {
            "text": "default",
            "value": "default"
          },
          "definition": "label_values(pgwatch_settings_configured,cluster)",
          "label": "Cluster name",
          "name": "cluster_name",
          "options": [],
          "query": {
            "qryType": 1,
            "query": "label_values(pgwatch_settings_configured,cluster)",
            "refId": "PrometheusVariableQueryEditor-VariableQuery"
          },
          "refresh": 1,
          "regex": "",
          "type": "query"
        },
        {
          "current": {
            "text": "5.78.159.160",
            "value": "5.78.159.160"
          },
          "definition": "label_values(pgwatch_settings_configured{cluster=\"$cluster_name\"},node_name)",
          "label": "Node name",
          "name": "node_name",
          "options": [],
          "query": {
            "qryType": 1,
            "query": "label_values(pgwatch_settings_configured{cluster=\"$cluster_name\"},node_name)",
            "refId": "PrometheusVariableQueryEditor-VariableQuery"
          },
          "refresh": 1,
          "regex": "",
          "type": "query"
        },
        {
          "current": {
            "text": "postgres",
            "value": "postgres"
          },
          "definition": "label_values(pgwatch_pg_database_wraparound_age_datfrozenxid{cluster=\"$cluster_name\", node_name=\"$node_name\", datname!=\"template1\"},datname)",
          "label": "DB name",
          "name": "db_name",
          "options": [],
          "query": {
            "qryType": 1,
            "query": "label_values(pgwatch_pg_database_wraparound_age_datfrozenxid{cluster=\"$cluster_name\", node_name=\"$node_name\", datname!=\"template1\"},datname)",
            "refId": "PrometheusVariableQueryEditor-VariableQuery"
          },
          "refresh": 1,
          "regex": "",
          "type": "query"
        },
        {
          "current": {
            "text": "All",
            "value": "$__all"
          },
          "definition": "label_values(pgwatch_pg_class_relation_size_bytes,schemaname)",
          "includeAll": true,
          "label": "Schema name",
          "name": "schema_name",
          "options": [],
          "query": {
            "qryType": 1,
            "query": "label_values(pgwatch_pg_class_relation_size_bytes,schemaname)",
            "refId": "PrometheusVariableQueryEditor-VariableQuery"
          },
          "refresh": 1,
          "regex": "",
          "type": "query"
        },
        {
          "current": {
            "text": "10",
            "value": "10"
          },
          "label": "Top N tables",
          "name": "top_n",
          "options": [
            {
              "selected": false,
              "text": "5",
              "value": "5"
            },
            {
              "selected": true,
              "text": "10",
              "value": "10"
            },
            {
              "selected": false,
              "text": "15",
              "value": "15"
            },
            {
              "selected": false,
              "text": "20",
              "value": "20"
            }
          ],
          "query": "5,10,15,20",
          "type": "custom"
        }
      ]
    },
    "time": {
      "from": "now-12h",
      "to": "now"
    },
    "timepicker": {},
    "timezone": "utc",
    "title": "09. Top tables overview",
    "uid": "92657f2a-985b-4d1a-99ed-2fac6e0c53e2",
    "version": 10
  }